inenvcache/__init__.py
inenvcache/src/__init__.py
inenvcache/src/in_env_cache.py
inenvcache-0.0.100.dist-info/LICENSE-AGPL
inenvcache-0.0.100.dist-info/LICENSE-COMMERCIAL-PERPETUAL
inenvcache-0.0.100.dist-info/LICENSE-COMMERCIAL-YEARLY
inenvcache-0.0.100.dist-info/METADATA
inenvcache-0.0.100.dist-info/WHEEL
inenvcache-0.0.100.dist-info/top_level.txt
inenvcache-0.0.100.dist-info/RECORD
