Metadata-Version: 2.1
Name: inenvcache
Version: 0.0.100
Summary: A caching framework to cache object across pods within an environment  
Home-page: https://github.com/shouryashashank/InEnvCache
Author: shouryashashank
Author-email: shouryashashank@gmail.com
License: AGPLv3+
Classifier: License :: OSI Approved :: GNU Affero General Public License v3 or later (AGPLv3+)
Classifier: Programming Language :: Python :: 3.10
Classifier: Operating System :: OS Independent
Requires-Python: >=3.10
License-File: LICENSE-AGPL
License-File: LICENSE-COMMERCIAL-PERPETUAL
License-File: LICENSE-COMMERCIAL-YEARLY
Requires-Dist: bson >=0.5.10
Requires-Dist: pycryptodome >=3.20.0
Requires-Dist: json >=2.0.9
Provides-Extra: dev
Requires-Dist: pytest >=7.0 ; extra == 'dev'
Requires-Dist: twine >=4.0.2 ; extra == 'dev'
